CrossDown/Core.py
CrossDown/Define.py
CrossDown/Extra.py
CrossDown/__init__.py
CrossDown-3.2.4.dist-info/LICENSE
CrossDown-3.2.4.dist-info/METADATA
CrossDown-3.2.4.dist-info/WHEEL
CrossDown-3.2.4.dist-info/top_level.txt
CrossDown-3.2.4.dist-info/RECORD
