Metadata-Version: 2.1
Name: CrossDown
Version: 3.2.4
Summary: CrossDark's MarkDown
Home-page: https://github.com/CrossDark/CrossDown
Author: CrossDark
Author-email: liuhanbo333@icloud.com
Classifier: Programming Language :: Python :: 3.11
Classifier: Programming Language :: Python :: 3.12
Classifier: License :: OSI Approved :: MIT License
Classifier: Operating System :: OS Independent
License-File: LICENSE
Requires-Dist: markdown
Requires-Dist: matplotlib
Requires-Dist: numpy
